longclaw
