Metadata-Version: 2.0
Name: longclaw
Version: 1.0.1
Summary: A shop for wagtail cms
Home-page: https://github.com/JamesRamm/longclaw
Author: James Ramm
Author-email: jamessramm@gmail.com
License: MIT
Keywords: longclaw
Platform: UNKNOWN
Classifier: Development Status :: 3 - Alpha
Classifier: Framework :: Django
Classifier: Framework :: Django :: 2.0
Classifier: Intended Audience :: Developers
Classifier: License :: OSI Approved :: BSD License
Classifier: Natural Language :: English
Classifier: Programming Language :: Python :: 3
Classifier: Programming Language :: Python :: 3.3
Classifier: Programming Language :: Python :: 3.4
Classifier: Programming Language :: Python :: 3.5
Requires-Dist: django-countries (>=5.3.2)
Requires-Dist: django-extensions (>=2.1.4)
Requires-Dist: django-ipware (>=2.1.0)
Requires-Dist: django (>=2.1)
Requires-Dist: djangorestframework (>=3.9.0)
Requires-Dist: wagtail (>=2.3)
